mogos/__init__.py
mogos-0.0.1.dist-info/METADATA
mogos-0.0.1.dist-info/WHEEL
mogos-0.0.1.dist-info/top_level.txt
mogos-0.0.1.dist-info/RECORD
